python_copilot_docs_hook/__init__.py
python_copilot_docs_hook/main.py
python_copilot_docs_hook-0.1.22.dist-info/METADATA
python_copilot_docs_hook-0.1.22.dist-info/WHEEL
python_copilot_docs_hook-0.1.22.dist-info/entry_points.txt
python_copilot_docs_hook-0.1.22.dist-info/top_level.txt
python_copilot_docs_hook-0.1.22.dist-info/RECORD
